pyqcat_viper/Viper.cpython-310-x86_64-linux-gnu.so
pyqcat_viper/Viper.pyi
pyqcat_viper/__init__.py
pyqcat_viper/optimizer.py
pyqcat_viper-0.1.0.dist-info/METADATA
pyqcat_viper-0.1.0.dist-info/WHEEL
pyqcat_viper-0.1.0.dist-info/top_level.txt
pyqcat_viper-0.1.0.dist-info/RECORD
